.appveyor.yml
.coveragerc
.gitignore
.readthedocs.yml
.style.yapf
.travis.yml
CHEATSHEET.rst
LICENSE
MANIFEST.in
Makefile
README.rst
pyproject.toml
setup.cfg
setup.py
ci/rtd-requirements.txt
ci/test-requirements.txt
ci/travis.sh
docs/Makefile
docs/make.bat
docs/source/conf.py
docs/source/history.rst
docs/source/index.rst
docs/source/_static/.gitkeep
newsfragments/.gitkeep
newsfragments/README.rst
tests/__init__.py
tests/conftest.py
tests/test_mockserver.py
wago/__init__.py
wago/server.py
wago.egg-info/PKG-INFO
wago.egg-info/SOURCES.txt
wago.egg-info/dependency_links.txt
wago.egg-info/requires.txt
wago.egg-info/top_level.txt