Metadata-Version: 1.2
Name: wago
Version: 0.10.0
Summary: Access I/O on Wago controllers
Home-page: http://github.com/M-o-a-T/wago
Author: Matthias Urlichs
Author-email: matthias@urlichs.de
License: GPLv3 or later
Keywords: iot
Platform: UNKNOWN
Classifier: License :: OSI Approved :: GNU General Public License v3 or later (GPLv3+)
Classifier: Operating System :: POSIX :: Linux
Classifier: Programming Language :: Python :: 3 :: Only
Classifier: Programming Language :: Python :: 3.6
Classifier: Programming Language :: Python :: 3.7
Classifier: Programming Language :: Python :: Implementation :: CPython
Classifier: Programming Language :: Python :: Implementation :: PyPy
Classifier: Framework :: Trio
Requires-Python: >=3.6
